odoo/addons/l10n_th_account_tax_inter_company/README.rst
odoo/addons/l10n_th_account_tax_inter_company/__init__.py
odoo/addons/l10n_th_account_tax_inter_company/__manifest__.py
odoo/addons/l10n_th_account_tax_inter_company/i18n/l10n_th_account_tax_inter_company.pot
odoo/addons/l10n_th_account_tax_inter_company/models/__init__.py
odoo/addons/l10n_th_account_tax_inter_company/models/account_move.py
odoo/addons/l10n_th_account_tax_inter_company/readme/CONTRIBUTORS.rst
odoo/addons/l10n_th_account_tax_inter_company/readme/DESCRIPTION.rst
odoo/addons/l10n_th_account_tax_inter_company/readme/USAGE.rst
odoo/addons/l10n_th_account_tax_inter_company/static/description/icon.png
odoo/addons/l10n_th_account_tax_inter_company/static/description/index.html
odoo/addons/l10n_th_account_tax_inter_company/tests/__init__.py
odoo/addons/l10n_th_account_tax_inter_company/tests/test_tax_invoice_inter_company.py
odoo_addon_l10n_th_account_tax_inter_company-15.0.1.0.0.2.dist-info/METADATA
odoo_addon_l10n_th_account_tax_inter_company-15.0.1.0.0.2.dist-info/WHEEL
odoo_addon_l10n_th_account_tax_inter_company-15.0.1.0.0.2.dist-info/top_level.txt
odoo_addon_l10n_th_account_tax_inter_company-15.0.1.0.0.2.dist-info/RECORD
